setup.py
yuan_cheng_package/person.py
yuan_cheng_package/test.py
yuan_cheng_package/yuancheng.py
yuan_cheng_package.egg-info/PKG-INFO
yuan_cheng_package.egg-info/SOURCES.txt
yuan_cheng_package.egg-info/dependency_links.txt
yuan_cheng_package.egg-info/top_level.txt